goblin/__init__.py
goblin/abc.py
goblin/app.py
goblin/element.py
goblin/exception.py
goblin/manager.py
goblin/mapper.py
goblin/properties.py
goblin/provider.py
goblin/session.py
goblin/version.py
goblin/driver/__init__.py
goblin/fileio/__init__.py
goblin/fileio/graphson.py
goblin-2.2.3.dist-info/LICENSE
goblin-2.2.3.dist-info/METADATA
goblin-2.2.3.dist-info/NOTICE
goblin-2.2.3.dist-info/WHEEL
goblin-2.2.3.dist-info/top_level.txt
goblin-2.2.3.dist-info/RECORD
